jreq/__init__.py
jreq/jreq.py
jreq-1.1.0.dist-info/LICENSE
jreq-1.1.0.dist-info/METADATA
jreq-1.1.0.dist-info/WHEEL
jreq-1.1.0.dist-info/top_level.txt
jreq-1.1.0.dist-info/RECORD
